susuio/__init__.py
susuio-0.0.2.dist-info/LICENSE
susuio-0.0.2.dist-info/METADATA
susuio-0.0.2.dist-info/WHEEL
susuio-0.0.2.dist-info/top_level.txt
susuio-0.0.2.dist-info/RECORD
