Metadata-Version: 2.1
Name: susuio
Version: 0.0.2
Summary: First
Home-page: UNKNOWN
Author: UNKNOWN
Author-email: <jorbfreire@gmail.com>
License: UNKNOWN
Keywords: python,io
Platform: UNKNOWN
Classifier: Development Status :: 1 - Planning
Classifier: Intended Audience :: Developers
Classifier: Programming Language :: Python :: 3
Classifier: Operating System :: Unix
Classifier: Operating System :: MacOS :: MacOS X
Classifier: Operating System :: Microsoft :: Windows
Requires-Dist: fs
Requires-Dist: numpy
